README.rst
setup.py
ipydb/__init__.py
ipydb/asciitable.py
ipydb/completion.py
ipydb/engine.py
ipydb/magic.py
ipydb/plugin.py
ipydb/utils.py
ipydb.egg-info/PKG-INFO
ipydb.egg-info/SOURCES.txt
ipydb.egg-info/dependency_links.txt
ipydb.egg-info/not-zip-safe
ipydb.egg-info/requires.txt
ipydb.egg-info/top_level.txt
ipydb/metadata/__init__.py
ipydb/metadata/model.py
ipydb/metadata/persist.py