Metadata-Version: 1.1
Name: ipydb
Version: 0.0.2
Summary: An IPython extension to help you write and run SQL statements
Home-page: http://github.com/jaysw/ipydb
Author: Jay Sweeney
Author-email: writetojay@gmail.com
License: Apache 2.0
Platform: UNKNOWN
Classifier: Development Status :: 4 - Beta
Classifier: Intended Audience :: Developers
Classifier: Natural Language :: English
Classifier: License :: OSI Approved :: Apache Software License
Classifier: Programming Language :: Python
Classifier: Programming Language :: Python :: 2.6
Classifier: Programming Language :: Python :: 2.7
Classifier: Environment :: Console
Classifier: Framework :: IPython
Classifier: Topic :: Database
